h5io_browser/__init__.py
h5io_browser/_version.py
h5io_browser/base.py
h5io_browser/future.py
h5io_browser/pointer.py
h5io_browser-0.2.9.dist-info/METADATA
h5io_browser-0.2.9.dist-info/WHEEL
h5io_browser-0.2.9.dist-info/licenses/LICENSE
h5io_browser-0.2.9.dist-info/RECORD
