Metadata-Version: 2.4
Name: h5io_browser
Version: 0.2.9
Summary: Easy navigation and data storage for HDF5
Project-URL: Homepage, https://github.com/h5io/h5io_browser
Project-URL: Documentation, https://github.com/h5io/h5io_browser
Project-URL: Repository, https://github.com/h5io/h5io_browser
Author-email: Jan Janssen <janssen@mpie.de>
License: BSD 3-Clause License
License-File: LICENSE
Keywords: h5io,hdf5
Classifier: Development Status :: 5 - Production/Stable
Classifier: Intended Audience :: Science/Research
Classifier: License :: OSI Approved :: BSD License
Classifier: Operating System :: OS Independent
Classifier: Programming Language :: Python :: 3.9
Classifier: Programming Language :: Python :: 3.10
Classifier: Programming Language :: Python :: 3.11
Classifier: Programming Language :: Python :: 3.12
Classifier: Programming Language :: Python :: 3.13
Classifier: Programming Language :: Python :: 3.14
Classifier: Topic :: Scientific/Engineering :: Physics
Requires-Python: >=3.9
Requires-Dist: h5io<=0.2.5,>=0.2.2
Requires-Dist: h5py<=3.15.1,>=3.6.0
Requires-Dist: numpy<=2.4.1,>=1.23.5
Requires-Dist: pandas<=3.0.0,>=1.5.3
Provides-Extra: pytables
Requires-Dist: tables==3.10.2; extra == 'pytables'
